Workbook

Sheet Raw Data
A1: Invoice ID | B1: Branch | C1: City | D1: Customer type | E1: Gender | F1: Product line | G1: Unit price | H1: Quantity | I1: Tax 5% | J1: Total | K1: Date | L1: Time | M1: Payment | N1: cogs | O1: gross margin percentage | P1: gross income | Q1: Rating | R1: Corrected Dates
A2: C189-0001 | B2: C | C2: Naypyitaw | D2: Member | E2: Female | F2: Fashion accessories | G2: 34.75 | H2: 4 | I2: 6.95 | J2: 145.95 | K2: 01/18/2019 | L2: 11:50 | M2: Ewallet | N2: 139 | O2: 4.7619 | P2: 6.95 | Q2: 9.4 | R2: =DATEVALUE(K2) -> 43483
A3: C765-0002 | B3: C | C3: Naypyitaw | D3: Normal | E3: Female | F3: Health and beauty | G3: 18.43 | H3: 4 | I3: 3.69 | J3: 77.41 | K3: 03/06/2019 | L3: 19:00 | M3: Ewallet | N3: 73.72 | O3: 4.7619 | P3: 3.69 | Q3: 5.2 | R3: =DATEVALUE(K3) -> 43530
A4: C881-0003 | B4: C | C4: Naypyitaw | D4: Normal | E4: Female | F4: Sports and travel | G4: 63.03 | H4: 1 | I4: 3.15 | J4: 66.18 | K4: 01/21/2019 | L4: 16:25 | M4: Credit card | N4: 63.03 | O4: 4.7619 | P4: 3.15 | Q4: 4.9 | R4: =DATEVALUE(K4) -> 43486
A5: B227-0004 | B5: B | C5: Mandalay | D5: Member | E5: Female | F5: Sports and travel | G5: 18.7 | H5: 6 | I5: 5.61 | J5: 117.81 | K5: 03/19/2019 | L5: 14:00 | M5: Ewallet | N5: 112.2 | O5: 4.7619 | P5: 5.61 | Q5: 6.8 | R5: =DATEVALUE(K5) -> 43543
A6: B333-0005 | B6: B | C6: Mandalay | D6: Member | E6: Male | F6: Fashion accessories | G6: 65.67 | H6: 6 | I6: 19.7 | J6: 413.72 | K6: 03/15/2019 | L6: 13:55 | M6: Cash | N6: 394.02 | O6: 4.7619 | P6: 19.7 | Q6: 4.3 | R6: =DATEVALUE(K6) -> 43539
A7: B786-0006 | B7: B | C7: Mandalay | D7: Member | E7: Female | F7: Health and beauty | G7: 44.21 | H7: 8 | I7: 17.68 | J7: 371.36 | K7: 03/23/2019 | L7: 15:10 | M7: Credit card | N7: 353.68 | O7: 4.7619 | P7: 17.68 | Q7: 6.1 | R7: =DATEVALUE(K7) -> 43547
A8: B324-0007 | B8: B | C8: Mandalay | D8: Member | E8: Female | F8: Food and beverages | G8: 75.62 | H8: 3 | I8: 11.34 | J8: 238.2 | K8: 03/01/2019 | L8: 16:20 | M8: Ewallet | N8: 226.86 | O8: 4.7619 | P8: 11.34 | Q8: 8.1 | R8: =DATEVALUE(K8) -> 43525
A9: C680-0008 | B9: C | C9: Naypyitaw | D9: Normal | E9: Female | F9: Electronic accessories | G9: 83.96 | H9: 6 | I9: 25.19 | J9: 528.95 | K9: 02/21/2019 | L9: 14:05 | M9: Cash | N9: 503.76 | O9: 4.7619 | P9: 25.19 | Q9: 9.5 | R9: =DATEVALUE(K9) -> 43517
A10: C651-0009 | B10: C | C10: Naypyitaw | D10: Normal | E10: Female | F10: Fashion accessories | G10: 54.93 | H10: 8 | I10: 21.97 | J10: 461.41 | K10: 01/19/2019 | L10: 14:10 | M10: Cash | N10: 439.44 | O10: 4.7619 | P10: 21.97 | Q10: 8.5 | R10: =DATEVALUE(K10) -> 43484
A11: B256-0010 | B11: B | C11: Mandalay | D11: Normal | E11: Male | F11: Home and lifestyle | G11: 29.74 | H11: 3 | I11: 4.46 | J11: 93.68 | K11: 03/07/2019 | L11: 17:05 | M11: Cash | N11: 89.22 | O11: 4.7619 | P11: 4.46 | Q11: 9.2 | R11: =DATEVALUE(K11) -> 43531
A12: C981-0011 | B12: C | C12: Naypyitaw | D12: Member | E12: Male | F12: Food and beverages | G12: 15.72 | H12: 7 | I12: 5.5 | J12: 115.54 | K12: 03/18/2019 | L12: 17:40 | M12: Credit card | N12: 110.04 | O12: 4.7619 | P12: 5.5 | Q12: 9.8 | R12: =DATEVALUE(K12) -> 43542
A13: A996-0012 | B13: A | C13: Yangon | D13: Member | E13: Male | F13: Fashion accessories | G13: 40.62 | H13: 5 | I13: 10.16 | J13: 213.26 | K13: 02/25/2019 | L13: 12:35 | M13: Cash | N13: 203.1 | O13: 4.7619 | P13: 10.16 | Q13: 9.7 | R13: =DATEVALUE(K13) -> 43521
... A1001: C251-1000 | B1001: C | C1001: Naypyitaw | D1001: Normal | E1001: Male | F1001: Fashion accessories | G1001: 25.33 | H1001: 3 | I1001: 3.8 | J1001: 79.79 | K1001: 03/16/2019 | L1001: 17:05 | M1001: Cash | N1001: 75.99 | O1001: 4.7619 | P1001: 3.8 | Q1001: 5.9 | R1001: =DATEVALUE(K1001) -> 43540

Sheet Data Checks
A1: Check | B1: Result
A2: Missing Cells | B2: =COUNTBLANK('Raw Data'!A2:Q1001) -> 0
A3: TotalMismatches | B3: {=SUMPRODUCT(--(ROUND('Raw Data'!J2:J1001-'Raw Data'!N2:N1001-'Raw Data'!I2:I1001,2)<>0))} -> 0
B6: =ISNUMBER('Raw Data'!K2) -> FALSE
B7: =ISNUMBER('Raw Data'!R2) -> TRUE

Sheet Sales Analysis
A1: Super market sales analysis
A3: Total transactions | B3: =COUNTA('Raw Data'!A2:A1001) -> 1000
A4: Total revenue | B4: =SUM('Raw Data'!J2:J1001) -> 324057.29
A5: Total units sold | B5: =SUM('Raw Data'!H2:H1001) -> 5591
A6: Average transaction value | B6: =AVERAGE('Raw Data'!J2:J1001) -> 324.05729
A7: Average customer rating | B7: =AVERAGE('Raw Data'!Q2:Q1001) -> 6.9834
A9: Product-line insights
A10: Highest revenue product line | B10: Fashion and accessories
A11: Lowest revenue product line | B11: Food and beverages
A12: Highest units sold product line | B12: Health and beauty
A14: Payment method insights
A15: Most-used payment method | B15: Credit Card
A16: Least-used payment method | B16: Cash
A18: Customer Analysis Insights
A19: Highest revenue customer type | B19: Normal
A20: Lowest revenue customer type | B20: Member
A22: Monthly Sales Insights
A23: Highest revenue month | B23: Jan
A24: Lowest revenue month | B24: Feb
A25: Monthly revenue trend | B25: Decrease,then partial recovery

Sheet Branch Analysis
A3: Row Labels | B3: Sum of Total
A4: B | B4: 113188.09
A5: C | B5: 110917.84 | O5: =MAX(B4:B6)-MIN(B4:B6) -> 13236.73
A6: A | B6: 99951.36
A7: Grand Total | B7: 324057.29

Sheet Product Analysis
A3: Product Line | B3: Sum of Total
A4: Fashion accessories | B4: 58398.13
A5: Home and lifestyle | B5: 57522.56
A6: Health and beauty | B6: 55650.91
A7: Sports and travel | B7: 52238.8
A8: Electronic accessories | B8: 51029.12
A9: Food and beverages | B9: 49217.77
A10: Grand Total | B10: 324057.29

Sheet Payment analysis
A3: Row Labels | B3: Count of Invoice ID | C3: Percentage
A4: Cash | B4: 306 | C4: =B4/1000 -> 0.306
A5: Credit card | B5: 360 | C5: =B5/1000 -> 0.36
A6: Ewallet | B6: 334 | C6: =B6/1000 -> 0.334
A7: Grand Total | B7: 1000

Sheet Customer analysis
A3: Row Labels | B3: Sum of Total
A4: Member | B4: 159230.63
A5: Normal | B5: 164826.66
A6: Grand Total | B6: 324057.29

Sheet Data Analysis
A3: Row Labels | B3: Sum of Total
A4: 2019 | B4: 324057.29
A5: Jan | B5: 120704.34
A6: Feb | B6: 100161.43
A7: Mar | B7: 103191.52
A8: Grand Total | B8: 324057.29
